imagpt/__init__.py
imagpt/cli.py
imagpt/config.py
imagpt/image_processing.py
imagpt/mcp_server.py
imagpt-0.7.0.dist-info/LICENSE
imagpt-0.7.0.dist-info/METADATA
imagpt-0.7.0.dist-info/WHEEL
imagpt-0.7.0.dist-info/entry_points.txt
imagpt-0.7.0.dist-info/RECORD
