Metadata-Version: 2.3
Name: imagpt
Version: 0.7.0
Summary: AI Image Generator with persistent configuration and MCP server support - Generate images using OpenAI API from prompt files, direct input, or through LLM integration
Author: Jacob Valdez
Author-email: jacobfv123@gmail.com
Requires-Python: >=3.12,<4.0
Classifier: Programming Language :: Python :: 3
Classifier: Programming Language :: Python :: 3.12
Classifier: Programming Language :: Python :: 3.13
Requires-Dist: Pillow (>=10.0.0,<11.0.0)
Requires-Dist: fastmcp (>=2.5.1,<3.0.0)
Requires-Dist: openai (>=1.82.0,<2.0.0)
Requires-Dist: pydantic (>=2.11.5,<3.0.0)
Requires-Dist: rich (>=14.0.0,<15.0.0)
Requires-Dist: tomli-w (>=1.2.0,<2.0.0)
Requires-Dist: typer[all] (>=0.16.0,<0.17.0)
